setup.py
alibabacloud_credentials_api/__init__.py
alibabacloud_credentials_api/models.py
alibabacloud_credentials_api.egg-info/PKG-INFO
alibabacloud_credentials_api.egg-info/SOURCES.txt
alibabacloud_credentials_api.egg-info/dependency_links.txt
alibabacloud_credentials_api.egg-info/top_level.txt